ZetcodeShujukuJiaochengChuyiFix1/README.md
ZetcodeShujukuJiaochengChuyiFix1/__init__.py
ZetcodeShujukuJiaochengChuyiFix1/__main__.py
ZetcodeShujukuJiaochengChuyiFix1/file.epub
ZetcodeShujukuJiaochengChuyiFix1/index.html
ZetcodeShujukuJiaochengChuyiFix1/css/__init__.py
ZetcodeShujukuJiaochengChuyiFix1/css/annotations.css
ZetcodeShujukuJiaochengChuyiFix1/css/main.css
ZetcodeShujukuJiaochengChuyiFix1/css/normalize.css
ZetcodeShujukuJiaochengChuyiFix1/css/popup.css
ZetcodeShujukuJiaochengChuyiFix1/font/__init__.py
ZetcodeShujukuJiaochengChuyiFix1/font/fontello.eot
ZetcodeShujukuJiaochengChuyiFix1/font/fontello.svg
ZetcodeShujukuJiaochengChuyiFix1/font/fontello.ttf
ZetcodeShujukuJiaochengChuyiFix1/font/fontello.woff
ZetcodeShujukuJiaochengChuyiFix1/img/__init__.py
ZetcodeShujukuJiaochengChuyiFix1/img/annotator-glyph-sprite.png
ZetcodeShujukuJiaochengChuyiFix1/img/annotator-icon-sprite.png
ZetcodeShujukuJiaochengChuyiFix1/img/apple-touch-icon.png
ZetcodeShujukuJiaochengChuyiFix1/img/cancelfullscreen.png
ZetcodeShujukuJiaochengChuyiFix1/img/close.png
ZetcodeShujukuJiaochengChuyiFix1/img/fullscreen.png
ZetcodeShujukuJiaochengChuyiFix1/img/loader.gif
ZetcodeShujukuJiaochengChuyiFix1/img/menu-icon.png
ZetcodeShujukuJiaochengChuyiFix1/img/save.png
ZetcodeShujukuJiaochengChuyiFix1/img/saved.png
ZetcodeShujukuJiaochengChuyiFix1/img/settings-s.png
ZetcodeShujukuJiaochengChuyiFix1/img/settings.png
ZetcodeShujukuJiaochengChuyiFix1/img/star.png
ZetcodeShujukuJiaochengChuyiFix1/js/__init__.py
ZetcodeShujukuJiaochengChuyiFix1/js/epub.js
ZetcodeShujukuJiaochengChuyiFix1/js/epub.min.js
ZetcodeShujukuJiaochengChuyiFix1/js/epub.min.map
ZetcodeShujukuJiaochengChuyiFix1/js/hooks.min.js
ZetcodeShujukuJiaochengChuyiFix1/js/hooks.min.map
ZetcodeShujukuJiaochengChuyiFix1/js/reader.js
ZetcodeShujukuJiaochengChuyiFix1/js/reader.js.map
ZetcodeShujukuJiaochengChuyiFix1/js/reader.min.js
ZetcodeShujukuJiaochengChuyiFix1/js/reader.min.map
ZetcodeShujukuJiaochengChuyiFix1/js/hooks/__init__.py
zetcode_shujuku_jiaocheng_chuyi_fix1-2025.3.23.0.dist-info/METADATA
zetcode_shujuku_jiaocheng_chuyi_fix1-2025.3.23.0.dist-info/WHEEL
zetcode_shujuku_jiaocheng_chuyi_fix1-2025.3.23.0.dist-info/entry_points.txt
zetcode_shujuku_jiaocheng_chuyi_fix1-2025.3.23.0.dist-info/top_level.txt
zetcode_shujuku_jiaocheng_chuyi_fix1-2025.3.23.0.dist-info/RECORD
